.coveragerc
.gitignore
AUTHORS.rst
CHANGELOG.rst
LICENSE.txt
README.rst
requirements.txt
setup.cfg
setup.py
tox.ini
.vscode/settings.json
docs/Makefile
docs/authors.rst
docs/changelog.rst
docs/conf.py
docs/index.rst
docs/license.rst
docs/_static/.gitignore
src/describe_variable/__init__.py
src/describe_variable/describer.py
src/describe_variable/helpers.py
src/describe_variable/main.py
src/describe_variable/tools.py
src/describe_variable.egg-info/PKG-INFO
src/describe_variable.egg-info/SOURCES.txt
src/describe_variable.egg-info/dependency_links.txt
src/describe_variable.egg-info/not-zip-safe
src/describe_variable.egg-info/requires.txt
src/describe_variable.egg-info/top_level.txt
tests/conftest.py
tests/test_skeleton.py