Metadata-Version: 2.1
Name: describe-variable
Version: 0.1.3
Summary: Add a short description here!
Home-page: https://github.com/MikeMajara/describe-variable
Author: Mike Majara
Author-email: fmiguel05@gmail.com
License: mit
Project-URL: Documentation, https://github.com/MikeMajara/describe-variable
Platform: any
Classifier: Development Status :: 4 - Beta
Classifier: Programming Language :: Python
Provides-Extra: testing
